mini_arcade_core/__init__.py
mini_arcade_core/backend/__init__.py
mini_arcade_core/backend/backend.py
mini_arcade_core/backend/events.py
mini_arcade_core/backend/keys.py
mini_arcade_core/backend/sdl_map.py
mini_arcade_core/backend/types.py
mini_arcade_core/bus.py
mini_arcade_core/engine/__init__.py
mini_arcade_core/engine/commands.py
mini_arcade_core/engine/game.py
mini_arcade_core/engine/render/__init__.py
mini_arcade_core/engine/render/context.py
mini_arcade_core/engine/render/effects/__init__.py
mini_arcade_core/engine/render/effects/base.py
mini_arcade_core/engine/render/effects/crt.py
mini_arcade_core/engine/render/effects/registry.py
mini_arcade_core/engine/render/effects/vignette.py
mini_arcade_core/engine/render/frame_packet.py
mini_arcade_core/engine/render/packet.py
mini_arcade_core/engine/render/passes/__init__.py
mini_arcade_core/engine/render/passes/base.py
mini_arcade_core/engine/render/passes/begin_frame.py
mini_arcade_core/engine/render/passes/end_frame.py
mini_arcade_core/engine/render/passes/lighting.py
mini_arcade_core/engine/render/passes/postfx.py
mini_arcade_core/engine/render/passes/ui.py
mini_arcade_core/engine/render/passes/world.py
mini_arcade_core/engine/render/pipeline.py
mini_arcade_core/engine/render/render_service.py
mini_arcade_core/engine/render/viewport.py
mini_arcade_core/managers/__init__.py
mini_arcade_core/managers/cheats.py
mini_arcade_core/managers/inputs.py
mini_arcade_core/runtime/__init__.py
mini_arcade_core/runtime/audio/__init__.py
mini_arcade_core/runtime/audio/audio_adapter.py
mini_arcade_core/runtime/audio/audio_port.py
mini_arcade_core/runtime/capture/__init__.py
mini_arcade_core/runtime/capture/capture_adapter.py
mini_arcade_core/runtime/capture/capture_port.py
mini_arcade_core/runtime/context.py
mini_arcade_core/runtime/file/__init__.py
mini_arcade_core/runtime/file/file_adapter.py
mini_arcade_core/runtime/file/file_port.py
mini_arcade_core/runtime/input/__init__.py
mini_arcade_core/runtime/input/input_adapter.py
mini_arcade_core-1.1.1.dist-info/METADATA
mini_arcade_core-1.1.1.dist-info/WHEEL
mini_arcade_core-1.1.1.dist-info/licenses/LICENSE
mini_arcade_core-1.1.1.dist-info/RECORD
