Metadata-Version: 2.4
Name: mini-arcade-core
Version: 1.1.1
Summary: Tiny scene-based game loop core for small arcade games.
License: Copyright (c) 2025 Santiago Rincón
License-File: LICENSE
Author: Santiago Rincon
Author-email: rincores@gmail.com
Requires-Python: >=3.9,<3.12
Classifier: License :: Other/Proprietary License
Classifier: Programming Language :: Python :: 3
Classifier: Programming Language :: Python :: 3.9
Classifier: Programming Language :: Python :: 3.10
Classifier: Programming Language :: Python :: 3.11
Provides-Extra: dev
Requires-Dist: black (>=24.10,<25.0) ; extra == "dev"
Requires-Dist: isort (>=5.13,<6.0) ; extra == "dev"
Requires-Dist: mypy (>=1.5,<2.0) ; extra == "dev"
Requires-Dist: pillow (<12)
Requires-Dist: pylint (>=3.3,<4.0) ; extra == "dev"
Requires-Dist: pytest (>=8.3,<9.0) ; extra == "dev"
Requires-Dist: pytest-cov (>=6.0,<7.0) ; extra == "dev"
